{
  "image_filename": "sample_000069.jpg",
  "image_size": [
    1080,
    782
  ],
  "vehicle_data": {
    "No. Pendaftaran": "BUR56 01",
    "Nama Pemilik": "PROF. LEE ONG",
    "No. Kad Pengenalan": "600813-13-1727",
    "Alamat": "759, PERSIARAN PETALING JAYA\nKLANG\n10999 SABAH",
    "Jenama": "KIA",
    "Model": "UNKNOWN",
    "Tahun Dibuat": "2006",
    "No. Enjin": "TF430116",
    "No. Casis": "PAJ36KC2075J2E1HP",
    "Warna": "OREN",
    "Jenis Bahan Api": "PETROL",
    "Isi Padu": "3026CC"
  },
  "annotations": {
    "fields": [
      {
        "label": "No. Pendaftaran",
        "bbox": [
          51,
          82,
          64,
          9
        ],
        "text": "BUR56 01",
        "field_type": "plate_number"
      },
      {
        "label": "Nama Pemilik",
        "bbox": [
          49,
          122,
          104,
          10
        ],
        "text": "PROF. LEE ONG",
        "field_type": "owner_name"
      },
      {
        "label": "No. Kad Pengenalan",
        "bbox": [
          54,
          159,
          94,
          10
        ],
        "text": "600813-13-1727",
        "field_type": "nric"
      },
      {
        "label": "Alamat",
        "bbox": [
          55,
          199,
          220,
          36
        ],
        "text": "759, PERSIARAN PETALING JAYA\nKLANG\n10999 SABAH",
        "field_type": "address"
      },
      {
        "label": "Jenama",
        "bbox": [
          49,
          303,
          25,
          10
        ],
        "text": "KIA",
        "field_type": "make"
      },
      {
        "label": "Model",
        "bbox": [
          217,
          299,
          56,
          8
        ],
        "text": "UNKNOWN",
        "field_type": "model"
      },
      {
        "label": "Tahun Dibuat",
        "bbox": [
          48,
          343,
          32,
          10
        ],
        "text": "2006",
        "field_type": "year"
      },
      {
        "label": "No. Enjin",
        "bbox": [
          53,
          383,
          66,
          10
        ],
        "text": "TF430116",
        "field_type": "engine_number"
      },
      {
        "label": "No. Casis",
        "bbox": [
          48,
          421,
          136,
          9
        ],
        "text": "PAJ36KC2075J2E1HP",
        "field_type": "chassis_number"
      },
      {
        "label": "Warna",
        "bbox": [
          53,
          460,
          32,
          8
        ],
        "text": "OREN",
        "field_type": "color"
      },
      {
        "label": "Jenis Bahan Api",
        "bbox": [
          216,
          461,
          48,
          8
        ],
        "text": "PETROL",
        "field_type": "fuel_type"
      },
      {
        "label": "Isi Padu",
        "bbox": [
          46,
          500,
          52,
          10
        ],
        "text": "3026CC",
        "field_type": "engine_capacity"
      }
    ]
  }
}