{
  "image_filename": "sample_000035.jpg",
  "image_size": [
    1080,
    782
  ],
  "vehicle_data": {
    "No. Pendaftaran": "PPN10 19",
    "Nama Pemilik": "PROF. LAKSHMI A/P KRISHNAN",
    "No. Kad Pengenalan": "591224-02-8584",
    "Alamat": "201, TAMAN KAJANG\nAMPANG\n72376 MELAKA",
    "Jenama": "BMW",
    "Model": "UNKNOWN",
    "Tahun Dibuat": "2007",
    "No. Enjin": "JM404952",
    "No. Casis": "CYUWC2NPJCJ3WM82Z",
    "Warna": "EMAS",
    "Jenis Bahan Api": "DIESEL",
    "Isi Padu": "3085CC"
  },
  "annotations": {
    "fields": [
      {
        "label": "No. Pendaftaran",
        "bbox": [
          49,
          77,
          58,
          10
        ],
        "text": "PPN10 19",
        "field_type": "plate_number"
      },
      {
        "label": "Nama Pemilik",
        "bbox": [
          45,
          118,
          209,
          10
        ],
        "text": "PROF. LAKSHMI A/P KRISHNAN",
        "field_type": "owner_name"
      },
      {
        "label": "No. Kad Pengenalan",
        "bbox": [
          52,
          160,
          112,
          9
        ],
        "text": "591224-02-8584",
        "field_type": "nric"
      },
      {
        "label": "Alamat",
        "bbox": [
          54,
          200,
          139,
          36
        ],
        "text": "201, TAMAN KAJANG\nAMPANG\n72376 MELAKA",
        "field_type": "address"
      },
      {
        "label": "Jenama",
        "bbox": [
          54,
          297,
          35,
          10
        ],
        "text": "BMW",
        "field_type": "make"
      },
      {
        "label": "Model",
        "bbox": [
          216,
          301,
          73,
          10
        ],
        "text": "UNKNOWN",
        "field_type": "model"
      },
      {
        "label": "Tahun Dibuat",
        "bbox": [
          45,
          338,
          28,
          10
        ],
        "text": "2007",
        "field_type": "year"
      },
      {
        "label": "No. Enjin",
        "bbox": [
          53,
          381,
          59,
          11
        ],
        "text": "JM404952",
        "field_type": "engine_number"
      },
      {
        "label": "No. Casis",
        "bbox": [
          49,
          422,
          150,
          10
        ],
        "text": "CYUWC2NPJCJ3WM82Z",
        "field_type": "chassis_number"
      },
      {
        "label": "Warna",
        "bbox": [
          48,
          460,
          32,
          8
        ],
        "text": "EMAS",
        "field_type": "color"
      },
      {
        "label": "Jenis Bahan Api",
        "bbox": [
          224,
          463,
          49,
          10
        ],
        "text": "DIESEL",
        "field_type": "fuel_type"
      },
      {
        "label": "Isi Padu",
        "bbox": [
          52,
          499,
          48,
          9
        ],
        "text": "3085CC",
        "field_type": "engine_capacity"
      }
    ]
  }
}