{
  "image_filename": "sample_000115.jpg",
  "image_size": [
    1080,
    782
  ],
  "vehicle_data": {
    "No. Pendaftaran": "AVV18 95",
    "Nama Pemilik": "EN. RAHMAN",
    "No. Kad Pengenalan": "930516-07-8077",
    "Alamat": "896, TAMAN PETALING JAYA\nPETALING JAYA\n61839 KELANTAN",
    "Jenama": "MITSUBISHI",
    "Model": "UNKNOWN",
    "Tahun Dibuat": "2011",
    "No. Enjin": "MU070907",
    "No. Casis": "30D7DT95TPHTRBG2P",
    "Warna": "MERAH",
    "Jenis Bahan Api": "HYBRID",
    "Isi Padu": "3073CC"
  },
  "annotations": {
    "fields": [
      {
        "label": "No. Pendaftaran",
        "bbox": [
          50,
          77,
          65,
          9
        ],
        "text": "AVV18 95",
        "field_type": "plate_number"
      },
      {
        "label": "Nama Pemilik",
        "bbox": [
          46,
          119,
          80,
          8
        ],
        "text": "EN. RAHMAN",
        "field_type": "owner_name"
      },
      {
        "label": "No. Kad Pengenalan",
        "bbox": [
          47,
          163,
          112,
          9
        ],
        "text": "930516-07-8077",
        "field_type": "nric"
      },
      {
        "label": "Alamat",
        "bbox": [
          50,
          200,
          193,
          30
        ],
        "text": "896, TAMAN PETALING JAYA\nPETALING JAYA\n61839 KELANTAN",
        "field_type": "address"
      },
      {
        "label": "Jenama",
        "bbox": [
          51,
          301,
          80,
          8
        ],
        "text": "MITSUBISHI",
        "field_type": "make"
      },
      {
        "label": "Model",
        "bbox": [
          215,
          298,
          73,
          10
        ],
        "text": "UNKNOWN",
        "field_type": "model"
      },
      {
        "label": "Tahun Dibuat",
        "bbox": [
          53,
          341,
          32,
          10
        ],
        "text": "2011",
        "field_type": "year"
      },
      {
        "label": "No. Enjin",
        "bbox": [
          45,
          377,
          64,
          9
        ],
        "text": "MU070907",
        "field_type": "engine_number"
      },
      {
        "label": "No. Casis",
        "bbox": [
          53,
          419,
          143,
          11
        ],
        "text": "30D7DT95TPHTRBG2P",
        "field_type": "chassis_number"
      },
      {
        "label": "Warna",
        "bbox": [
          52,
          458,
          40,
          8
        ],
        "text": "MERAH",
        "field_type": "color"
      },
      {
        "label": "Jenis Bahan Api",
        "bbox": [
          219,
          458,
          52,
          10
        ],
        "text": "HYBRID",
        "field_type": "fuel_type"
      },
      {
        "label": "Isi Padu",
        "bbox": [
          51,
          501,
          48,
          9
        ],
        "text": "3073CC",
        "field_type": "engine_capacity"
      }
    ]
  }
}