{
  "image_filename": "sample_000547.jpg",
  "image_size": [
    1080,
    782
  ],
  "vehicle_data": {
    "No. Pendaftaran": "BBS37 09",
    "Nama Pemilik": "DR. CHONG CHAN",
    "No. Kad Pengenalan": "610830-16-1244",
    "Alamat": "877, LEBUH SEREMBAN\nKLANG\n74140 TERENGGANU",
    "Jenama": "AUDI",
    "Model": "UNKNOWN",
    "Tahun Dibuat": "2018",
    "No. Enjin": "EE691805",
    "No. Casis": "G78V318U6JV1GGKNY",
    "Warna": "HIJAU",
    "Jenis Bahan Api": "HYBRID",
    "Isi Padu": "3318CC"
  },
  "annotations": {
    "fields": [
      {
        "label": "No. Pendaftaran",
        "bbox": [
          46,
          83,
          63,
          10
        ],
        "text": "BBS37 09",
        "field_type": "plate_number"
      },
      {
        "label": "Nama Pemilik",
        "bbox": [
          46,
          118,
          119,
          10
        ],
        "text": "DR. CHONG CHAN",
        "field_type": "owner_name"
      },
      {
        "label": "No. Kad Pengenalan",
        "bbox": [
          45,
          160,
          94,
          10
        ],
        "text": "610830-16-1244",
        "field_type": "nric"
      },
      {
        "label": "Alamat",
        "bbox": [
          45,
          200,
          156,
          36
        ],
        "text": "877, LEBUH SEREMBAN\nKLANG\n74140 TERENGGANU",
        "field_type": "address"
      },
      {
        "label": "Jenama",
        "bbox": [
          45,
          297,
          33,
          8
        ],
        "text": "AUDI",
        "field_type": "make"
      },
      {
        "label": "Model",
        "bbox": [
          219,
          298,
          73,
          10
        ],
        "text": "UNKNOWN",
        "field_type": "model"
      },
      {
        "label": "Tahun Dibuat",
        "bbox": [
          45,
          338,
          28,
          10
        ],
        "text": "2018",
        "field_type": "year"
      },
      {
        "label": "No. Enjin",
        "bbox": [
          52,
          381,
          66,
          10
        ],
        "text": "EE691805",
        "field_type": "engine_number"
      },
      {
        "label": "No. Casis",
        "bbox": [
          54,
          423,
          153,
          10
        ],
        "text": "G78V318U6JV1GGKNY",
        "field_type": "chassis_number"
      },
      {
        "label": "Warna",
        "bbox": [
          51,
          459,
          40,
          8
        ],
        "text": "HIJAU",
        "field_type": "color"
      },
      {
        "label": "Jenis Bahan Api",
        "bbox": [
          222,
          463,
          53,
          10
        ],
        "text": "HYBRID",
        "field_type": "fuel_type"
      },
      {
        "label": "Isi Padu",
        "bbox": [
          48,
          503,
          48,
          9
        ],
        "text": "3318CC",
        "field_type": "engine_capacity"
      }
    ]
  }
}